{"name":"","children":[{"name":"","children":[{"name":"Neither","children":[],"tokens":["Neither"]},{"name":"Lorillard","children":[],"tokens":["Lorillard"]},{"name":"nor","children":[],"tokens":["nor"]},{"name":"","children":[{"name":"","children":[{"name":"the","children":[],"tokens":["the"]},{"name":"researchers","children":[],"tokens":["researchers"]}],"tokens":["the","researchers"]},{"name":"","children":[{"name":"who","children":[],"tokens":["who"]},{"name":"","children":[{"name":"*T*-3","children":[],"tokens":["*T*-3"]},{"name":"","children":[{"name":"studied","children":[],"tokens":["studied"]},{"name":"","children":[{"name":"the","children":[],"tokens":["the"]},{"name":"workers","children":[],"tokens":["workers"]}],"tokens":["the","workers"]}],"tokens":["studied","the","workers"]}],"tokens":["*T*-3","studied","the","workers"]}],"tokens":["who","*T*-3","studied","the","workers"]}],"tokens":["the","researchers","who","*T*-3","studied","the","workers"]}],"tokens":["Neither","Lorillard","nor","the","researchers","who","*T*-3","studied","the","workers"]},{"name":"","children":[{"name":"were","children":[],"tokens":["were"]},{"name":"","children":[{"name":"aware","children":[],"tokens":["aware"]},{"name":"","children":[{"name":"of","children":[],"tokens":["of"]},{"name":"","children":[{"name":"","children":[{"name":"any","children":[],"tokens":["any"]},{"name":"research","children":[],"tokens":["research"]}],"tokens":["any","research"]},{"name":"","children":[{"name":"on","children":[],"tokens":["on"]},{"name":"","children":[{"name":"smokers","children":[],"tokens":["smokers"]},{"name":"","children":[{"name":"of","children":[],"tokens":["of"]},{"name":"","children":[{"name":"the","children":[],"tokens":["the"]},{"name":"Kent","children":[],"tokens":["Kent"]},{"name":"cigarettes","children":[],"tokens":["cigarettes"]}],"tokens":["the","Kent","cigarettes"]}],"tokens":["of","the","Kent","cigarettes"]}],"tokens":["smokers","of","the","Kent","cigarettes"]}],"tokens":["on","smokers","of","the","Kent","cigarettes"]}],"tokens":["any","research","on","smokers","of","the","Kent","cigarettes"]}],"tokens":["of","any","research","on","smokers","of","the","Kent","cigarettes"]}],"tokens":["aware","of","any","research","on","smokers","of","the","Kent","cigarettes"]}],"tokens":["were","aware","of","any","research","on","smokers","of","the","Kent","cigarettes"]},{"name":".","children":[],"tokens":["."]}],"tokens":["Neither","Lorillard","nor","the","researchers","who","*T*-3","studied","the","workers","were","aware","of","any","research","on","smokers","of","the","Kent","cigarettes","."]}