{"name":"","children":[{"name":"``","children":[],"tokens":["``"]},{"name":"","children":[{"name":"We","children":[],"tokens":["We"]},{"name":"","children":[{"name":"have","children":[],"tokens":["have"]},{"name":"","children":[{"name":"","children":[{"name":"no","children":[],"tokens":["no"]},{"name":"useful","children":[],"tokens":["useful"]},{"name":"information","children":[],"tokens":["information"]}],"tokens":["no","useful","information"]},{"name":"","children":[{"name":"on","children":[],"tokens":["on"]},{"name":"","children":[{"name":"whether","children":[],"tokens":["whether"]},{"name":"","children":[{"name":"users","children":[],"tokens":["users"]},{"name":"","children":[{"name":"are","children":[],"tokens":["are"]},{"name":"","children":[{"name":"at","children":[],"tokens":["at"]},{"name":"risk","children":[],"tokens":["risk"]}],"tokens":["at","risk"]}],"tokens":["are","at","risk"]}],"tokens":["users","are","at","risk"]}],"tokens":["whether","users","are","at","risk"]}],"tokens":["on","whether","users","are","at","risk"]}],"tokens":["no","useful","information","on","whether","users","are","at","risk"]}],"tokens":["have","no","useful","information","on","whether","users","are","at","risk"]}],"tokens":["We","have","no","useful","information","on","whether","users","are","at","risk"]},{"name":",","children":[],"tokens":[","]},{"name":"\u0027\u0027","children":[],"tokens":["\u0027\u0027"]},{"name":"","children":[{"name":"said","children":[],"tokens":["said"]},{"name":"*T*-1","children":[],"tokens":["*T*-1"]}],"tokens":["said","*T*-1"]},{"name":"","children":[{"name":"","children":[{"name":"James","children":[],"tokens":["James"]},{"name":"A.","children":[],"tokens":["A."]},{"name":"Talcott","children":[],"tokens":["Talcott"]}],"tokens":["James","A.","Talcott"]},{"name":"","children":[{"name":"of","children":[],"tokens":["of"]},{"name":"","children":[{"name":"","children":[{"name":"Boston","children":[],"tokens":["Boston"]},{"name":"\u0027s","children":[],"tokens":["\u0027s"]}],"tokens":["Boston","\u0027s"]},{"name":"Dana-Farber","children":[],"tokens":["Dana-Farber"]},{"name":"Cancer","children":[],"tokens":["Cancer"]},{"name":"Institute","children":[],"tokens":["Institute"]}],"tokens":["Boston","\u0027s","Dana-Farber","Cancer","Institute"]}],"tokens":["of","Boston","\u0027s","Dana-Farber","Cancer","Institute"]}],"tokens":["James","A.","Talcott","of","Boston","\u0027s","Dana-Farber","Cancer","Institute"]},{"name":".","children":[],"tokens":["."]}],"tokens":["``","We","have","no","useful","information","on","whether","users","are","at","risk",",","\u0027\u0027","said","*T*-1","James","A.","Talcott","of","Boston","\u0027s","Dana-Farber","Cancer","Institute","."]}